LICENSE
README.md
setup.py
http_spammer/__init__.py
http_spammer/contraints.py
http_spammer/metrics.py
http_spammer/request.py
http_spammer/spammer.py
http_spammer/timing.py
http_spammer/worker.py
http_spammer.egg-info/PKG-INFO
http_spammer.egg-info/SOURCES.txt
http_spammer.egg-info/dependency_links.txt
http_spammer.egg-info/requires.txt
http_spammer.egg-info/top_level.txt